sendou/__init__.py
sendou/client.py
sendou/models/__init__.py
sendou/models/badge.py
sendou/models/baseModel.py
sendou/models/calendarEntry.py
sendou/models/organization.py
sendou/models/plusServer.py
sendou/models/stageMapList.py
sendou/models/tournament/__init__.py
sendou/models/tournament/bracket/Standing.py
sendou/models/tournament/bracket/__init__.py
sendou/models/tournament/bracket/bracket.py
sendou/models/tournament/bracket/type.py
sendou/models/tournament/match.py
sendou/models/tournament/team.py
sendou/models/tournament/tournament.py
sendou/models/user.py
sendou/requests/__init__.py
sendou/requests/client.py
sendou_py-1.2.12.dist-info/METADATA
sendou_py-1.2.12.dist-info/WHEEL
sendou_py-1.2.12.dist-info/RECORD
