Metadata-Version: 2.1
Name: sendou-py
Version: 1.2.12
Summary: An async Python library for Sendou.ink
Home-page: https://github.com/IPLSplatoon/sendou.py/
License: MIT
Keywords: splatoon,sendou.ink
Author: Vincent Lee
Author-email: vlee@iplabs.ink
Requires-Python: >=3.10,<4.0
Classifier: Development Status :: 4 - Beta
Classifier: Framework :: AsyncIO
Classifier: License :: OSI Approved :: MIT License
Classifier: Programming Language :: Python :: 3
Classifier: Programming Language :: Python :: 3.10
Classifier: Programming Language :: Python :: 3.11
Classifier: Programming Language :: Python :: 3.12
Classifier: Programming Language :: Python :: 3.13
Classifier: Topic :: Software Development :: Libraries :: Python Modules
Requires-Dist: aiohttp-client-cache (>=0.12.0,<0.13.0)
Requires-Dist: python-dateutil (>=2.8.2,<3.0.0)
Project-URL: Documentation, https://sendou.opensource.iplabs.work/
Project-URL: Repository, https://github.com/IPLSplatoon/sendou.py/
